cistem/__init__.py
cistem/bibtex.py
cistem/cistem_logo.png
cistem/constants.py
cistem/protocols.conf
cistem/wizards.py
cistem/convert/__init__.py
cistem/convert/convert.py
cistem/convert/dataimport.py
cistem/protocols/__init__.py
cistem/protocols/program_ctffind.py
cistem/protocols/protocol_ctffind.py
cistem/protocols/protocol_picking.py
cistem/protocols/protocol_refine2d.py
cistem/protocols/protocol_tomo_resample.py
cistem/protocols/protocol_ts_ctffind.py
cistem/protocols/protocol_ts_resample.py
cistem/protocols/protocol_unblur.py
cistem/tests/__init__.py
cistem/tests/test_protocols_cistem.py
cistem/tests/test_protocols_cistem_movies.py
cistem/tests/tomo_tests.py
cistem/viewers/__init__.py
cistem/viewers/tomo_viewers.py
cistem/viewers/viewers.py
scipion_em_cistem-3.10.1.dist-info/LICENSE
scipion_em_cistem-3.10.1.dist-info/METADATA
scipion_em_cistem-3.10.1.dist-info/WHEEL
scipion_em_cistem-3.10.1.dist-info/entry_points.txt
scipion_em_cistem-3.10.1.dist-info/top_level.txt
scipion_em_cistem-3.10.1.dist-info/RECORD
