Metadata-Version: 2.1
Name: scipion-em-cistem
Version: 3.10.1
Summary: Plugin to use cisTEM programs within the Scipion framework
Author-email: Scipion Team <scipion@cnb.csic.es>
License: GNU General Public License v3 (GPLv3)
Project-URL: Homepage, https://github.com/scipion-em/scipion-em-cistem
Project-URL: Issues, https://github.com/scipion-em/scipion-em-cistem/issues
Keywords: scipion,cryoem,cryoet,imageprocessing,scipion-3.0
Classifier: Development Status :: 5 - Production/Stable
Classifier: License :: OSI Approved :: GNU General Public License v3 (GPLv3)
Classifier: Programming Language :: Python :: 3
Requires-Python: >=3.8
License-File: LICENSE
Requires-Dist: scipion-em
Requires-Dist: scipion-pyworkflow
